kinms_fitter/__init__.py
kinms_fitter/diskThick_funcs.py
kinms_fitter/kinms_fitter.py
kinms_fitter/kinms_fitter_old.py
kinms_fitter/prior_funcs.py
kinms_fitter/sb_profs.py
kinms_fitter/skySampler.py
kinms_fitter/transformClouds.py
kinms_fitter/velocity_profs.py
kinms_fitter/warp_funcs.py
kinms_fitter-0.5.12.dist-info/LICENSE
kinms_fitter-0.5.12.dist-info/METADATA
kinms_fitter-0.5.12.dist-info/WHEEL
kinms_fitter-0.5.12.dist-info/top_level.txt
kinms_fitter-0.5.12.dist-info/zip-safe
kinms_fitter-0.5.12.dist-info/RECORD
