Metadata-Version: 2.1
Name: kinms_fitter
Version: 0.5.12
Summary: Wrapper for KinMSpy that automates most common galaxy fitting tasks
Home-page: https://github.com/TimothyADavis/KinMS_fitter
Author: Timothy A. Davis
Author-email: DavisT@cardiff.ac.uk
License: GNU GPLv3
Classifier: Development Status :: 3 - Alpha
Classifier: License :: OSI Approved :: GNU General Public License v3 (GPLv3)
Classifier: Programming Language :: Python :: 3
Classifier: Operating System :: OS Independent
License-File: LICENSE
Requires-Dist: numpy
Requires-Dist: gastimator >=0.5.2
Requires-Dist: astropy
Requires-Dist: matplotlib
Requires-Dist: spectral-cube
Requires-Dist: scipy >=1.3.3
Requires-Dist: jampy
Requires-Dist: kinms >=3.0.11
